clientOIDCAduneo/BaseServer.py
clientOIDCAduneo/Configuration.py
clientOIDCAduneo/CryptoTools.py
clientOIDCAduneo/Help.py
clientOIDCAduneo/OIDCClientAdmin.py
clientOIDCAduneo/OIDCClientAdminGuide.py
clientOIDCAduneo/OIDCClientLogin.py
clientOIDCAduneo/OIDCClientLogout.py
clientOIDCAduneo/SAMLClientAdmin.py
clientOIDCAduneo/SAMLClientLogin.py
clientOIDCAduneo/SAMLClientLogout.py
clientOIDCAduneo/Template.py
clientOIDCAduneo/__init__.py
clientOIDCAduneo/__main__.py
clientOIDCAduneo/main.py
clientOIDCAduneo/server.py
clientOIDCAduneo/conf/_localhost.crt
clientOIDCAduneo/conf/_localhost.key
clientOIDCAduneo/conf/fedclient.cnf
clientOIDCAduneo/conf/fedclient.key
clientOIDCAduneo/conf/help.json
clientOIDCAduneo/static/css/aduneo.css
clientOIDCAduneo/static/css/dragWindow.css
clientOIDCAduneo/static/images/aduneo.png
clientOIDCAduneo/static/images/copy.png
clientOIDCAduneo/static/images/favicon.png
clientOIDCAduneo/static/images/help.png
clientOIDCAduneo/static/images/home.png
clientOIDCAduneo/static/images/logged.png
clientOIDCAduneo/static/images/moins.png
clientOIDCAduneo/static/images/plus.png
clientOIDCAduneo/static/javascript/SAMLClientAdmin.js
clientOIDCAduneo/static/javascript/help.js
clientOIDCAduneo/static/javascript/resultTable.js
clientOIDCAduneo/templates/guide.htm
clientOIDCAduneo/templates/test.html
clientOIDCAduneo/tests/template.py
client_test_oidc_theo_aduneo-0.0.8.dist-info/LICENSE
client_test_oidc_theo_aduneo-0.0.8.dist-info/METADATA
client_test_oidc_theo_aduneo-0.0.8.dist-info/WHEEL
client_test_oidc_theo_aduneo-0.0.8.dist-info/top_level.txt
client_test_oidc_theo_aduneo-0.0.8.dist-info/RECORD
