Metadata-Version: 2.1
Name: client-test-oidc-theo-aduneo
Version: 0.0.8
Summary: test package Client OIDC Aduneo
Home-page: https://github.com/pypa/sampleproject
Author: Theo Bedouet
Author-email: theo.bedouet@aduneo.com
License: UNKNOWN
Project-URL: Bug Tracker, https://github.com/pypa/sampleproject/issues
Platform: UNKNOWN
Classifier: Programming Language :: Python :: 3
Classifier: License :: OSI Approved :: GNU Affero General Public License v3
Classifier: Operating System :: OS Independent
Requires-Python: >=3.6
License-File: LICENSE
Requires-Dist: requests
Requires-Dist: wheel
Requires-Dist: pyopenssl
Requires-Dist: jwcrypto
Requires-Dist: lxml
Requires-Dist: xmlsec
